[
    [
        {
            "title": "Breakfast & Check-In",
            "time": "8:00 AM",
            "description": "Come down to the Centre for Dialogue for free breakfast and check-in to get your badges ahead of the Summit.",
            "color": "#F6D9D7"
        },
        {
            "title": "Welcome Presentation",
            "time": "9:00 AM",
            "speaker": "MC",
            "description": "Land acknowledgement and overview of the Summit program.",
            "color": "#F6D9D7"
        },
        {
            "title": "City Pulse: What Makes A City Attractive",
            "time": "9:30 AM",
            "speaker": "Aftab Erfan & panelists",
            "description": "A panel discussion on the the 5 main work attractions in cities + Q & A.",
            "color": "#B8D98D"
        },
        {
            "title": "Speed Bingo Fun!",
            "time": "10:30 AM",
            "description": "Test your knowledge on topics of Urban Work!",
            "color": "#F6D9D7"
        },
        {
            "title": "Coffee Break",
            "time": "11:15 AM",
            "color": "#FBD166"
        },
        {
            "title": "Workshop: Part A - Where are we AT today? (1)",
            "time": "11:30 AM",
            "description": "A data-driven workshop utilizing pre-summit information and resources for collaborative group work, defining the current state of work and opportunities.",
            "color": "#F2695D"
        },
        {
            "title": "Lunch Break",
            "time": "12:30 AM",
            "color": "#FBD166"
        },
        {
            "title": "Redefining the Future: A deep dive into the work ecosystem in Canada",
            "time": "1:30 PM",
            "speaker": "George Benson & panelists",
            "description": "A panel discussion on the the 5 main work dimensions in cities + Q & A.",
            "color": "#B8D98D"
        },
        {
            "title": "Coffee Break",
            "time": "2:30 PM",
            "color": "#FBD166"
        },
        {
            "title": "Workshop: Part A - Where are we AT today? (1)",
            "time": "3:00 PM",
            "speaker": "John Smith",
            "description": "Report back presentations from groups.",
            "color": "#F2695D"
        },
        {
            "title": "Workshop: Part A- Where are we AT today? (2)",
            "time": "3:30 PM",
            "speaker": "John Smith",
            "description": "Group work using the panel info, data and resources provided in the pre-summit phase to define the current state-of-work and opportunities.",
            "color": "#F2695D"
        },
        {
            "title": "Workshop: Part A- Where are we AT today? (2)",
            "time": "4:30 PM",
            "speaker": "John Smith",
            "description": "Report back presentations from groups.",
            "color": "#F2695D"
        },
        {
            "title": "Where are we AT? - Wrap Up",
            "time": "5:00 PM",
            "speaker": "John Smith",
            "description": "Voting opportunities to move onto the next stages.",
            "color": "#F2695D"
        },
        {
            "title": "End of Day 1 Wrap Up",
            "time": "5:15 PM",
            "speaker": "John Smith",
            "description": "Present as a group your findings during the earlier workshop on where the city is AT today",
            "color": "#F6D9D7"
        },
        {
            "title": "Dinner",
            "time": "6:00 PM",
            "description": "Choose your own adventure dinner, spend this time how you would like!",
            "color": "#FBD166"
        }
    ],
    [
        {
            "title": "Breakfast & Check-In",
            "time": "8:00 AM",
            "description": "Come down to the Centre for Dialogue for free breakfast and check-in for Day 2 of the Summit.",
            "color": "#F6D9D7"
        },
        {
            "title": "Day 2 Overview",
            "time": "9:00 AM",
            "description": "Going over the agenda and expectations for Day 2",
            "color": "#F6D9D7"
        },
        {
            "title": "Workshop: Part B - Where do we want to BE?",
            "time": "9:15 AM",
            "speaker": "John Smith",
            "description": "Creative visioning session with group work to expand on the voted opportunities for the future of work and cities.",
            "color": "#F2695D"
        },
        {
            "title": "Coffee Break",
            "time": "10:30 AM",
            "color": "#FBD166"
        },
        {
            "title": "Workshop: Part C - What can we CREATE?(1)",
            "time": "11:00 AM",
            "description": "Session to flesh out and cluster all possible ideas based on opportunity areas coming from Parts A and B.",
            "color": "#F2695D"
        },
        {
            "title": "Guest Speaker",
            "time": "12:30 PM",
            "speaker": "w/ Hon. Andrew Mercier",
            "description": "A talk by Hon. Andrew Mercier, Minister of State for Workforce Development + Q & A with audience.",
            "color": "#B8D98D"
        },
        {
            "title": "Lunch",
            "time": "1:00 PM",
            "color": "#FBD166"
        },
        {
            "title": "Workshop: Part C- What can we CREATE?(2)",
            "time": "2:30 PM",
            "description": "Group work to combine clusters of ideas and to enhance ideas to early stage concepts.",
            "color": "#F2695D"
        },
        {
            "title": "Coffee Break",
            "time": "3:30 PM",
            "color": "#FBD166"
        },
        {
            "title": "Workshop: Part C - What can we CREATE?(3)",
            "time": "3:45 PM",
            "description": "Collective voting session to form more defined concepts and form groups based on concepts.",
            "color": "#F2695D"
        },
        {
            "title": "End of Day 2 Wrap Up",
            "time": "5:15 PM",
            "description": "Summary of the day and overview of the next day.",
            "color": "#F6D9D7"
        },
        {
            "title": "Dinner",
            "time": "6:00 PM",
            "description": "Free time for you to grab dinner or explore the city!",
            "color": "#FBD166"
        }
    ],
    [
        {
            "title": "Breakfast & Check-In",
            "time": "8:00 AM",
            "color": "#F6D9D7"
        },
        {
            "title": "Day 3 Overview",
            "time": "9:00 AM",
            "description": "Going over the agenda and expectations for Day 3",
            "color": "#F6D9D7"
        },
        {
            "title": "Guest Speaker",
            "time": "9:15 AM",
            "speaker": "w/ Youth Leader + Q & A",
            "description": "TBD.",
            "color": "#B8D98D"
        },
        {
            "title": "Coffee Break",
            "time": "10:00 AM",
            "color": "#FBD166"
        },
        {
            "title": "Workshop: Part D - What can we DO next to get to where we want to be?",
            "time": "10:30 AM",
            "description": "Group work to identify resources and brainstorm for project proposal to showcase with a medium of each groups choice.",
            "color": "#F2695D"
        },
        {
            "title": "Lunch",
            "time": "12:00 PM",
            "color": "#FBD166"
        },
        {
            "title": "Workshop: Part D - Project Development",
            "time": "1:30 PM",
            "description": "With mentors, groups will fine tune their proposals, create their pitch and practice.",
            "color": "#F2695D"
        },
        {
            "title": "Coffee Break",
            "time": "3:30 PM",
            "color": "#FBD166"
        },
        {
            "title": "Continuation of project development and Shortlisting",
            "time": "3:45 PM",
            "description": "Groups will continue working on their pitch and there will be voting to shortlist the teams moving to the next stage.",
            "color": "#F2695D"
        },
        {
            "title": "Pitch Competition",
            "time": "5:00 PM",
            "speaker":"TBA",
            "description": "5-6 shortlisted teams will present their pitch either through a fair model or to an expert panel that provides feedback.",
            "color": "#B8D98D"
        },
        {
            "title": "Talks",
            "time": "6:00 PMgi",
            "speaker":"TBA",
            "description": "Brief talks featuring Minister Bailey, RBC, and LinkedIn panel.",
            "color": "#B8D98D"
        },
        {
            "title": "Dinner",
            "time": "6:45 PM",
            "description": "Catered Dinner .",
            "color": "#FBD166"
        },
        {
            "title": "Micro-grant Winners Announced + Celebration",
            "time": "7:45 PM",
            "color": "#FBD166"
        }
    ]
]
